{"name":"Search norway northen lights in google","id":"google-search;search-norway-northen-lights-in-google","testSteps":[{"number":1,"description":"Given that Antonio open google browser","duration":6805,"startTime":"2018-11-30T00:03:07.258-05:00[America/Bogota]","screenshots":[{"screenshot":"29e8117f9e0698b567705eee1fedfb3dba6d42aa11e1e545c148cc940f2f927e.png"}],"result":"SUCCESS","precondition":false,"children":[{"number":2,"description":"Antonio opens the browser on Google Home Page","duration":6230,"startTime":"2018-11-30T00:03:07.580-05:00[America/Bogota]","screenshots":[{"screenshot":"1a56bc61aafc554d6b22eaf9914681d9ff821f41709fa8481bdd370d823c34a8.png"}],"result":"SUCCESS","precondition":false,"children":[{"number":3,"description":"Antonio opens the Google home page","duration":5943,"startTime":"2018-11-30T00:03:07.604-05:00[America/Bogota]","screenshots":[{"screenshot":"1a56bc61aafc554d6b22eaf9914681d9ff821f41709fa8481bdd370d823c34a8.png"}],"result":"SUCCESS","precondition":false}]}]},{"number":4,"description":"When he search Norway Northen lights","duration":4200,"startTime":"2018-11-30T00:03:14.064-05:00[America/Bogota]","screenshots":[{"screenshot":"fe4a330a9fdf5791d8e088c44ba465e6b0bf34e8cb62d4322bcd1fcc6fc55791.png"}],"result":"SUCCESS","precondition":false,"children":[{"number":5,"description":"Antonio enters \u0027Norway Northen Lights\u0027 into Google search box","duration":782,"startTime":"2018-11-30T00:03:14.378-05:00[America/Bogota]","screenshots":[{"screenshot":"1a56bc61aafc554d6b22eaf9914681d9ff821f41709fa8481bdd370d823c34a8.png"},{"screenshot":"1070a7431600fd4df440c95245c49343f31f9cb01b60fe84d2f518009ee57444.png"}],"result":"SUCCESS","precondition":false},{"number":6,"description":"Antonio clicks on Google search buttom","duration":2823,"startTime":"2018-11-30T00:03:15.166-05:00[America/Bogota]","screenshots":[{"screenshot":"b1012e23b8d61e3b962d05230ec49cb929721adc8247d723a9f774b5608a4e78.png"},{"screenshot":"fe4a330a9fdf5791d8e088c44ba465e6b0bf34e8cb62d4322bcd1fcc6fc55791.png"}],"result":"SUCCESS","precondition":false}]},{"number":7,"description":"Then he should see the results","duration":1257,"startTime":"2018-11-30T00:03:18.265-05:00[America/Bogota]","screenshots":[{"screenshot":"fe4a330a9fdf5791d8e088c44ba465e6b0bf34e8cb62d4322bcd1fcc6fc55791.png"}],"result":"SUCCESS","precondition":false,"children":[{"number":8,"description":"Then the result should be \u0027\u0027","duration":612,"startTime":"2018-11-30T00:03:18.633-05:00[America/Bogota]","screenshots":[{"screenshot":"fe4a330a9fdf5791d8e088c44ba465e6b0bf34e8cb62d4322bcd1fcc6fc55791.png"}],"result":"SUCCESS","precondition":false}]}],"userStory":{"id":"google-search","storyName":"Google Search","path":"src/test/resources/features/google_search.feature","narrative":"  As a Web User\n  I want to use google\n  to search somentihing","type":"feature"},"featureTag":{"name":"Features/Google Search","type":"feature"},"title":"Search norway northen lights in google","tags":[{"name":"Google search","type":"feature"}],"startTime":"2018-11-30T00:03:06.796-05:00[America/Bogota]","duration":12727,"projectKey":"","sessionId":"395fa97b12d203980a2c7337719f9d40","driver":"chrome","manual":false,"testSource":"Cucumber","actors":[{"name":"Antonio","can":["browse the web with FIREFOX"]}],"result":"SUCCESS"}